{
  "total": 20,
  "limit": 10,
  "offset": 0,
  "items": [
    {
      "category": "xueqiu",
      "title": "对古井贡酒25年和26Q1财报的看法",
      "link": "http://xueqiu.com/7368170779/386469504",
      "published_time": "2026-04-29 09:43:38",
      "raw_content": "",
      "ai_summary": "对古井贡酒2025年和2026年Q1财报的预测与分析。",
      "ai_tags": [
        "古井贡酒",
        "财报",
        "白酒"
      ],
      "ai_importance": 3
    },
    {
      "category": "xueqiu",
      "title": "细看紫金矿业勘查找矿这看家本领",
      "link": "http://xueqiu.com/5205526918/386435201",
      "published_time": "2026-04-29 09:44:09",
      "raw_content": "",
      "ai_summary": "紫金矿业在勘查找矿方面的核心技术优势被详细分析。",
      "ai_tags": [
        "紫金矿业",
        "勘查",
        "找矿"
      ],
      "ai_importance": 3
    },
    {
      "category": "xueqiu",
      "title": "AI光通信不是向硅光演进，而是向PIC演进",
      "link": "http://xueqiu.com/8755156034/386285705",
      "published_time": "2026-04-29 09:44:40",
      "raw_content": "",
      "ai_summary": "AI光通信的发展方向是从硅光演进到PIC（光子集成电路）。",
      "ai_tags": [
        "AI光通信",
        "硅光",
        "PIC"
      ],
      "ai_importance": 2
    },
    {
      "category": "xueqiu",
      "title": "周期会来，周期会走",
      "link": "http://xueqiu.com/7913104177/386431059",
      "published_time": "2026-04-29 09:43:48",
      "raw_content": "",
      "ai_summary": "讨论经济周期必然到来和离去，强调周期规律。",
      "ai_tags": [
        "周期",
        "经济",
        "投资"
      ],
      "ai_importance": 2
    },
    {
      "category": "xueqiu",
      "title": "商品期货投资155年：收益不输美股，但从不均匀分配",
      "link": "http://xueqiu.com/3559889031/386434038",
      "published_time": "2026-04-29 09:44:03",
      "raw_content": "",
      "ai_summary": "商品期货投资155年历史显示收益不逊于美股，但分配不均。",
      "ai_tags": [
        "商品期货",
        "投资收益",
        "历史"
      ],
      "ai_importance": 2
    },
    {
      "category": "xueqiu",
      "title": "光芯片主线走势：基于四轮科技牛市的客观规律、概率判断与风险提示",
      "link": "http://xueqiu.com/2351470882/386557478",
      "published_time": "2026-04-29 09:44:22",
      "raw_content": "",
      "ai_summary": "基于四轮科技牛市规律，对光芯片主线走势进行概率判断与风险提示。",
      "ai_tags": [
        "光芯片",
        "科技牛市",
        "风险提示"
      ],
      "ai_importance": 2
    },
    {
      "category": "xueqiu",
      "title": "有色学习笔记（三）：黄金",
      "link": "http://xueqiu.com/5332385101/386565236",
      "published_time": "2026-04-29 09:44:34",
      "raw_content": "",
      "ai_summary": "学习笔记分享：有关有色金属中黄金的投资分析。",
      "ai_tags": [
        "有色",
        "黄金",
        "学习笔记"
      ],
      "ai_importance": 1
    },
    {
      "category": "xueqiu",
      "title": "年报一季报粗略印象",
      "link": "http://xueqiu.com/1516479974/386560812",
      "published_time": "2026-04-29 09:44:14",
      "raw_content": "",
      "ai_summary": "对上市公司年报和一季报的粗略印象和总结。",
      "ai_tags": [
        "年报",
        "一季报",
        "总结"
      ],
      "ai_importance": 1
    },
    {
      "category": "xueqiu",
      "title": "1.6T 光模块产业链调研纪要",
      "link": "http://xueqiu.com/4790816824/386151674",
      "published_time": "2026-04-28 09:25:09",
      "raw_content": "",
      "ai_summary": "1.6T光模块产业链调研纪要，涉及技术、供应商及市场前景。",
      "ai_tags": [
        "光模块",
        "1.6T",
        "产业链调研"
      ],
      "ai_importance": 4
    },
    {
      "category": "xueqiu",
      "title": "相比Waymo和特斯拉，曹操出行全要素闭环生态更接近Robotaxi终局",
      "link": "http://xueqiu.com/4118099716/386161928",
      "published_time": "2026-04-28 09:25:52",
      "raw_content": "",
      "ai_summary": "曹操出行的全要素闭环生态被认为比Waymo和特斯拉更接近Robotaxi终局。",
      "ai_tags": [
        "Robotaxi",
        "曹操出行",
        "Waymo",
        "特斯拉"
      ],
      "ai_importance": 4
    }
  ]
}
